cs/py3/__init__.py
cs/py3/_for2.py
cs/py3/_for3.py
cs/py3/tests.py
cs.py3-20220523.dist-info/METADATA
cs.py3-20220523.dist-info/WHEEL
cs.py3-20220523.dist-info/top_level.txt
cs.py3-20220523.dist-info/RECORD
